cdktf_cdktf_provider_snowflake/__init__.py
cdktf_cdktf_provider_snowflake/py.typed
cdktf_cdktf_provider_snowflake/_jsii/__init__.py
cdktf_cdktf_provider_snowflake/_jsii/provider-snowflake@15.8.1.jsii.tgz
cdktf_cdktf_provider_snowflake/account/__init__.py
cdktf_cdktf_provider_snowflake/account_authentication_policy_attachment/__init__.py
cdktf_cdktf_provider_snowflake/account_parameter/__init__.py
cdktf_cdktf_provider_snowflake/account_password_policy_attachment/__init__.py
cdktf_cdktf_provider_snowflake/account_role/__init__.py
cdktf_cdktf_provider_snowflake/alert/__init__.py
cdktf_cdktf_provider_snowflake/api_authentication_integration_with_authorization_code_grant/__init__.py
cdktf_cdktf_provider_snowflake/api_authentication_integration_with_client_credentials/__init__.py
cdktf_cdktf_provider_snowflake/api_authentication_integration_with_jwt_bearer/__init__.py
cdktf_cdktf_provider_snowflake/api_integration/__init__.py
cdktf_cdktf_provider_snowflake/authentication_policy/__init__.py
cdktf_cdktf_provider_snowflake/compute_pool/__init__.py
cdktf_cdktf_provider_snowflake/cortex_search_service/__init__.py
cdktf_cdktf_provider_snowflake/current_account/__init__.py
cdktf_cdktf_provider_snowflake/current_organization_account/__init__.py
cdktf_cdktf_provider_snowflake/data_snowflake_account_roles/__init__.py
cdktf_cdktf_provider_snowflake/data_snowflake_accounts/__init__.py
cdktf_cdktf_provider_snowflake/data_snowflake_alerts/__init__.py
cdktf_cdktf_provider_snowflake/data_snowflake_authentication_policies/__init__.py
cdktf_cdktf_provider_snowflake/data_snowflake_compute_pools/__init__.py
cdktf_cdktf_provider_snowflake/data_snowflake_connections/__init__.py
cdktf_cdktf_provider_snowflake/data_snowflake_cortex_search_services/__init__.py
cdktf_cdktf_provider_snowflake/data_snowflake_current_account/__init__.py
cdktf_cdktf_provider_snowflake/data_snowflake_current_role/__init__.py
cdktf_cdktf_provider_snowflake/data_snowflake_database/__init__.py
cdktf_cdktf_provider_snowflake-15.8.1.dist-info/LICENSE
cdktf_cdktf_provider_snowflake-15.8.1.dist-info/METADATA
cdktf_cdktf_provider_snowflake-15.8.1.dist-info/WHEEL
cdktf_cdktf_provider_snowflake-15.8.1.dist-info/top_level.txt
cdktf_cdktf_provider_snowflake-15.8.1.dist-info/RECORD
